{
  "pets": [
    {
      "id": 123456,
      "name": "Fluffy",
      "species": "Dog",
      "breed": "Golden Retriever",
      "age": 3,
      "color": "Golden",
      "sex": "Male",
      "location": "New York",
      "image": "https://cmsphoto.ww-cdn.com/superstatic/528641/art/default/13123810-30393538.jpg?v=1638241454"
    },
    {
      "id": 2,
      "name": "Whiskers",
      "species": "Cat",
      "breed": "Siamese",
      "age": 5,
      "color": "Cream",
      "sex": "Female",
      "location": "Los Angeles",
      "image": "https://cmsphoto.ww-cdn.com/superstatic/528641/art/default/64703245-47830929.jpg?v=1664763403"
    },
    {
      "id": 3,
      "name": "Max",
      "species": "Dog",
      "breed": "German Shepherd",
      "age": 2,
      "color": "Black and Tan",
      "sex": "Male",
      "location": "Chicago",
      "image": "https://cmsphoto.ww-cdn.com/superstatic/528641/art/default/69204530-48467142.jpg?v=1669685500"
    },
    {
      "id": 4,
      "name": "Bella",
      "species": "Cat",
      "breed": "Persian",
      "age": 4,
      "color": "White",
      "sex": "Female",
      "location": "Houston",
      "image": "https://cmsphoto.ww-cdn.com/superstatic/528641/art/default/10503002-17244080.jpg?v=1478033334"
    },
    {
      "id": 5,
      "name": "Rocky",
      "species": "Dog",
      "breed": "Boxer",
      "age": 1,
      "color": "Brindle",
      "sex": "Male",
      "location": "Philadelphia",
      "image": "https://cmsphoto.ww-cdn.com/superstatic/528641/art/default/10511995-17261463.jpg?v=1478133498"
    },
    {
      "id": 6,
      "name": "Oreo",
      "species": "Rabbit",
      "breed": "Dwarf Rabbit",
      "age": 2,
      "color": "Black and White",
      "sex": "Male",
      "location": "Phoenix",
      "image": "https://cmsphoto.ww-cdn.com/superstatic/528641/art/default/10554536-17347520.jpg?v=1478731255"
    },
    {
      "id": 7,
      "name": "Charlie",
      "species": "Bird",
      "breed": "Parrot",
      "age": 8,
      "color": "Multicolored",
      "sex": "Male",
      "location": "San Antonio",
      "image": "https://cmsphoto.ww-cdn.com/superstatic/528641/art/default/59544744-43736972.jpg?v=1634226080"
    }
  ]
}
